redbrick/__init__.py
redbrick/config.py
redbrick/dataset.py
redbrick/organization.py
redbrick/project.py
redbrick/py.typed
redbrick/version_check.py
redbrick/workspace.py
redbrick/cli/__init__.py
redbrick/cli/cli_base.py
redbrick/cli/project.py
redbrick/cli/public.py
redbrick/cli/command/__init__.py
redbrick/cli/command/clone.py
redbrick/cli/command/config.py
redbrick/cli/command/export.py
redbrick/cli/command/info.py
redbrick/cli/command/init.py
redbrick/cli/command/report.py
redbrick/cli/command/upload.py
redbrick/cli/entity/__init__.py
redbrick/cli/entity/cache.py
redbrick/cli/entity/conf.py
redbrick/cli/entity/creds.py
redbrick/cli/input/__init__.py
redbrick/cli/input/api_key.py
redbrick/cli/input/number.py
redbrick/cli/input/profile.py
redbrick/cli/input/select.py
redbrick/cli/input/text.py
redbrick/cli/input/url.py
redbrick/cli/input/uuid.py
redbrick/common/__init__.py
redbrick/common/client.py
redbrick/common/constants.py
redbrick/common/context.py
redbrick/common/dataset.py
redbrick/common/entities.py
redbrick/common/enums.py
redbrick/common/export.py
redbrick/common/labeling.py
redbrick/common/member.py
redbrick/common/project.py
redbrick/common/settings.py
redbrick/common/stage.py
redbrick/common/storage.py
redbrick/common/upload.py
redbrick/common/workspace.py
redbrick/export/__init__.py
redbrick/export/dataset.py
redbrick/export/public.py
redbrick/labeling/__init__.py
redbrick/labeling/public.py
redbrick/member/__init__.py
redbrick/member/team.py
redbrick/member/workforce.py
redbrick/repo/__init__.py
redbrick/repo/dataset.py
redbrick/repo/export.py
redbrick/repo/labeling.py
redbrick/repo/member.py
redbrick/repo/project.py
redbrick/repo/settings.py
redbrick/repo/shards.py
redbrick/repo/storage.py
redbrick/repo/upload.py
redbrick/repo/workspace.py
redbrick/settings/__init__.py
redbrick/settings/public.py
redbrick/stage/__init__.py
redbrick/stage/label.py
redbrick/stage/model.py
redbrick/stage/review.py
redbrick/storage/__init__.py
redbrick_sdk-2.31.0.dist-info/LICENSE
redbrick_sdk-2.31.0.dist-info/METADATA
redbrick_sdk-2.31.0.dist-info/WHEEL
redbrick_sdk-2.31.0.dist-info/entry_points.txt
redbrick_sdk-2.31.0.dist-info/top_level.txt
redbrick_sdk-2.31.0.dist-info/RECORD
