Metadata-Version: 2.1
Name: redbrick-sdk
Version: 2.31.0
Summary: RedBrick platform Python SDK!
License: MIT License
Project-URL: Homepage, https://www.redbrickai.com
Project-URL: Documentation, https://sdk.redbrickai.com
Project-URL: Changelog, https://docs.redbrickai.com/changelogs/redbrick-sdk-changelog
Keywords: redbrick
Classifier: Programming Language :: Python
Requires-Python: <3.15,>=3.10
License-File: LICENSE
Requires-Dist: aiofiles<25
Requires-Dist: aiohttp<4,>=3.10.5
Requires-Dist: dicom2nifti<3
Requires-Dist: inquirerpy<1
Requires-Dist: natsort<9,>=8.0.2
Requires-Dist: nest-asyncio<2,>=1.5.4
Requires-Dist: nibabel<6,>=5.3.2
Requires-Dist: numpy<3,>=2
Requires-Dist: packaging<25
Requires-Dist: Pillow<12,>=9.0.1
Requires-Dist: pydicom<4,>=2.4
Requires-Dist: pydicom-seg-rb<2,>=1
Requires-Dist: python-dateutil<3
Requires-Dist: requests<3,>=2.23.0
Requires-Dist: Rich<15
Requires-Dist: rt-utils<2
Requires-Dist: shtab<2
Requires-Dist: SimpleITK<3
Requires-Dist: tenacity<10
Requires-Dist: tqdm<5
Requires-Dist: typing-extensions<5
Provides-Extra: dev
Requires-Dist: black<=24.10.0; extra == "dev"
Requires-Dist: build<=1.2.2.post1; extra == "dev"
Requires-Dist: flake8<=7.1.1; extra == "dev"
Requires-Dist: gputil<=1.4.0; extra == "dev"
Requires-Dist: mypy<=1.13.0; extra == "dev"
Requires-Dist: mypy-extensions<=1.0.0; extra == "dev"
Requires-Dist: psutil<=6.1.0; extra == "dev"
Requires-Dist: pycodestyle<=2.12.1; extra == "dev"
Requires-Dist: pydocstyle<=6.3.0; extra == "dev"
Requires-Dist: pylint<=3.3.2; extra == "dev"
Requires-Dist: pytest<=8.3.4; extra == "dev"
Requires-Dist: pytest-asyncio<=0.25.0; extra == "dev"
Requires-Dist: pytest-cov<=6.0.0; extra == "dev"
Requires-Dist: pytest-randomly<=3.16.0; extra == "dev"
Requires-Dist: pytest-xdist<=3.6.1; extra == "dev"
Requires-Dist: pytest-xdist[psutil]<=3.6.1; extra == "dev"
Requires-Dist: setuptools<=75.6.0; extra == "dev"
Requires-Dist: wheel<=0.45.1; extra == "dev"
